pytest_proofy/__init__.py
pytest_proofy/config.py
pytest_proofy/plugin.py
pytest_proofy-0.1.2.dist-info/METADATA
pytest_proofy-0.1.2.dist-info/WHEEL
pytest_proofy-0.1.2.dist-info/entry_points.txt
pytest_proofy-0.1.2.dist-info/top_level.txt
pytest_proofy-0.1.2.dist-info/RECORD
