Metadata-Version: 2.4
Name: pytest-proofy
Version: 0.1.2
Summary: Pytest plugin for Proofy test reporting
Author-email: Proofy Team <team@proofy.dev>, Krzysztof Marmol <krzysztof.marmol@gmail.com>
License-Expression: Apache-2.0
Keywords: pytest,testing,proofy,reporting
Classifier: Development Status :: 4 - Beta
Classifier: Framework :: Pytest
Classifier: Intended Audience :: Developers
Classifier: Programming Language :: Python
Classifier: Programming Language :: Python :: 3
Classifier: Programming Language :: Python :: 3.10
Classifier: Programming Language :: Python :: 3.12
Classifier: Topic :: Software Development :: Testing
Requires-Python: >=3.10
Requires-Dist: pytest>=7.0.0
Requires-Dist: proofy-python>=0.1.2
Provides-Extra: dev
Requires-Dist: pytest-xdist>=3.0; extra == "dev"
Requires-Dist: pytest-cov>=4.1; extra == "dev"
Requires-Dist: coverage[toml]>=7.0; extra == "dev"
Requires-Dist: mypy>=1.10; extra == "dev"
Requires-Dist: types-requests>=2.25; extra == "dev"
